pynometrics/__init__.py
pynometrics/pynometrics.py
pynometrics-0.1.5.dist-info/LICENSE.txt
pynometrics-0.1.5.dist-info/METADATA
pynometrics-0.1.5.dist-info/WHEEL
pynometrics-0.1.5.dist-info/top_level.txt
pynometrics-0.1.5.dist-info/RECORD
