Metadata-Version: 2.1
Name: pynometrics
Version: 0.1.5
Summary: Includes functions for performing econometrics tasks
Home-page: https://github.com/G-Geofrey/econometric_package.git
Author: Geofrey Wanyama
Author-email: wanyamag17@gmail.com
License-File: LICENSE.txt
Requires-Dist: pandas
Requires-Dist: numpy
Requires-Dist: matplotlib
Requires-Dist: seaborn
Requires-Dist: stargazer
